Workbook
Name ProductosList: 'Escala de valor'!$A$7:$A$17

Sheet Instrucciones
A1: Calculadora Pedraza Ilustración
A2: Archivo consolidado: márgenes, descuentos, forecast, pedido a China y rotación de inventario. Agosto 2026.
A4: Este archivo junta en un solo lugar lo que hoy vive repartido: el catálogo con sus márgenes, una calculadora de descuento que avisa cuando el margen cae bajo el piso del 60%, el forecast de demanda de puzzles agosto-diciembre, la calculadora del pedido a China, y la rotación de inventario. Las celdas amarillas son las únicas pensadas para editar — el resto son fórmulas que se recalculan solas.
A6: Pestaña | B6: Qué contiene | C6: Qué se puede editar
A7: Escala de valor | B7: El catálogo completo (11 productos) con precio actual, precio nuevo, precio de comparación (cuando aplica) y margen en pesos y en porcentaje. Se pone en rojo cuando el margen cae bajo el 60%. | C7: La columna Costo unitario — cargar ahí los costos reales de tinta, papel, packaging y flete de cada producto.
A8: Simulador de descuento | B8: Elige un producto y un porcentaje de descuento, y calcula el precio final, el margen resultante y avisa si cae bajo el 60%. | C8: El producto (lista desplegable) y el porcentaje de descuento de cada fila.
A9: Forecast por producto | B9: La demanda de puzzles agosto-diciembre 2026, cruzando los tres canales (Shopify, Mercado Libre, B2B) en los cuatro escenarios, y el reparto de esa demanda por modelo (aves/cetáceos/hongos). | C9: Los tres canales de cada escenario, y el % de reparto por modelo si cambia el mix histórico.
A10: Pedido | B10: La calculadora del pedido a China: cuántas unidades pedir, cómo se reparten por modelo, cuánto cuesta en FOB y puesto en Chile, y cuánto es el anticipo del 30%. | C10: La cantidad total a pedir, el % de reparto por modelo, el tipo de cambio, el % de anticipo, el costo FOB unitario y el costo puesto en Chile.
A11: Rotación | B11: Unidades vendidas al mes por categoría, stock actual y meses de cobertura, con alerta cuando quedan menos de 2 meses de stock. | C11: El stock actual de cada categoría — cargarlo desde Shopify/Bsale para que la cobertura se calcule sola.
A13: Cómo leer los colores
B14: Celda de entrada — se edita libremente. El resto del archivo se recalcula solo.
B15: Alerta — el margen cayó bajo el piso del 60%, o la cobertura de stock bajó de 2 meses.
B16: Dentro del rango sano — margen sobre 60%, o cobertura sobre 2 meses.
A18: Fuente de los datos: docs/correcciones-felipe-2026-08-01.md (catálogo, precios y composición del pedido que llega el 15 de agosto), docs/forecast-pedido-2026-08-02.md (demanda y fechas límite), docs/datos-financieros-2025-2026.md (categorías de venta y deuda vigente), y lo decidido en la llamada del 5 de agosto de 2026 (rango del pedido 2.000-2.500, mini-puzzles, precios FOB, piso de margen 60%, precios nuevos de láminas). Preparado para Felipe — reunión del viernes 7 de agosto de 2026.

Sheet Escala de valor
A1: Escala de valor — catálogo y márgenes
A2: Precio actual, precio nuevo y margen de los 11 productos del catálogo. La columna Costo unitario es la que hay que completar.
A4: 🟢 Piso de margen fijado por Felipe: nunca bajar del 60%. La columna Margen % se pone en rojo automáticamente cuando cae bajo ese piso.
A6: Producto | B6: Precio actual (Shopify hoy) | C6: Precio nuevo | D6: Precio comparación (tachado, si aplica) | E6: Costo unitario (completar) | F6: Margen $ | G6: Margen % | H6: Alerta
A7: Botellas | B7: 28990 | C7: 32990 | F7: =IF(E7="","",C7-E7) | G7: =IF(E7="","",F7/C7) | H7: =IF(E7="","Falta costo",IF(G7<0.6,"⚠ BAJO 60%","✅ OK"))
A8: Calcetines | B8: 9390 | C8: 9990 | F8: =IF(E8="","",C8-E8) | G8: =IF(E8="","",F8/C8) | H8: =IF(E8="","Falta costo",IF(G8<0.6,"⚠ BAJO 60%","✅ OK"))
A9: Naipes | B9: 22990 | C9: 22990 | F9: =IF(E9="","",C9-E9) | G9: =IF(E9="","",F9/C9) | H9: =IF(E9="","Falta costo",IF(G9<0.6,"⚠ BAJO 60%","✅ OK"))
A10: Láminas 42×60 (grande) | B10: 48390 | C10: 42990 | D10: 52990 | F10: =IF(E10="","",C10-E10) | G10: =IF(E10="","",F10/C10) | H10: =IF(E10="","Falta costo",IF(G10<0.6,"⚠ BAJO 60%","✅ OK"))
A11: Láminas 33×50 (mediana) | B11: 36980 | C11: 32990 | D11: 49990 | F11: =IF(E11="","",C11-E11) | G11: =IF(E11="","",F11/C11) | H11: =IF(E11="","Falta costo",IF(G11<0.6,"⚠ BAJO 60%","✅ OK"))
A12: Libretas | B12: 17490 | C12: 18990 | F12: =IF(E12="","",C12-E12) | G12: =IF(E12="","",F12/C12) | H12: =IF(E12="","Falta costo",IF(G12<0.6,"⚠ BAJO 60%","✅ OK"))
A13: Llavero | B13: 8790 | C13: 9990 | F13: =IF(E13="","",C13-E13) | G13: =IF(E13="","",F13/C13) | H13: =IF(E13="","Falta costo",IF(G13<0.6,"⚠ BAJO 60%","✅ OK"))
A14: Pins | B14: 5490 | C14: 7990 | F14: =IF(E14="","",C14-E14) | G14: =IF(E14="","",F14/C14) | H14: =IF(E14="","Falta costo",IF(G14<0.6,"⚠ BAJO 60%","✅ OK"))
A15: Postales | B15: 10990 | C15: 11990 | F15: =IF(E15="","",C15-E15) | G15: =IF(E15="","",F15/C15) | H15: =IF(E15="","Falta costo",IF(G15<0.6,"⚠ BAJO 60%","✅ OK"))
A16: Puzzle (promedio 3 modelos) | B16: 27290 | C16: 29990 | E16: 7253 | F16: =IF(E16="","",C16-E16) | G16: =IF(E16="","",F16/C16) | H16: =IF(E16="","Falta costo",IF(G16<0.6,"⚠ BAJO 60%","✅ OK"))
A17: Totebag | B17: 16490 | C17: 17990 | F17: =IF(E17="","",C17-E17) | G17: =IF(E17="","",F17/C17) | H17: =IF(E17="","Falta costo",IF(G17<0.6,"⚠ BAJO 60%","✅ OK"))
A19: Fuente: docs/correcciones-felipe-2026-08-01.md, sección 6 (lista final de precios, definida por Felipe por benchmark de competencia, no por tramo). Precio comparación de láminas y el costo del puzzle: decididos en la llamada del 5 de agosto de 2026. El resto de los costos unitarios está pendiente de carga — sin costo, el margen queda en blanco a propósito (no se asume 100% de margen).

Sheet Simulador de descuento
A1: Simulador de descuento
A2: Elige un producto y un % de descuento: calcula el precio final y avisa si el margen cae bajo el 60%. Los precios y costos se traen solos desde Escala de valor.
A4: 🟡 Las filas sin costo cargado en Escala de valor muestran "Falta costo" — no se puede simular un margen que no se conoce.
A6: Producto | B6: Precio nuevo (automático) | C6: Costo unitario (automático) | D6: % Descuento (editable) | E6: Precio final | F6: Margen $ | G6: Margen % | H6: Alerta
A7: Botellas | B7: =IFERROR(INDEX('Escala de valor'!$C$7:$C$17,MATCH(A7,'Escala de valor'!$A$7:$A$17,0)),"") | C7: =IFERROR(INDEX('Escala de valor'!$E$7:$E$17,MATCH(A7,'Escala de valor'!$A$7:$A$17,0)),"") | D7: 0.1 | E7: =IF(B7="","",B7*(1-D7)) | F7: =IF(OR(B7="",C7="",C7=0),"",E7-C7) | G7: =IF(F7="","",IF(E7=0,"",F7/E7)) | H7: =IF(F7="","Falta costo",IF(G7<0.6,"⚠ CAE BAJO 60%","✅ OK, sobre el piso"))
A8: Calcetines | B8: =IFERROR(INDEX('Escala de valor'!$C$7:$C$17,MATCH(A8,'Escala de valor'!$A$7:$A$17,0)),"") | C8: =IFERROR(INDEX('Escala de valor'!$E$7:$E$17,MATCH(A8,'Escala de valor'!$A$7:$A$17,0)),"") | D8: 0.1 | E8: =IF(B8="","",B8*(1-D8)) | F8: =IF(OR(B8="",C8="",C8=0),"",E8-C8) | G8: =IF(F8="","",IF(E8=0,"",F8/E8)) | H8: =IF(F8="","Falta costo",IF(G8<0.6,"⚠ CAE BAJO 60%","✅ OK, sobre el piso"))
A9: Naipes | B9: =IFERROR(INDEX('Escala de valor'!$C$7:$C$17,MATCH(A9,'Escala de valor'!$A$7:$A$17,0)),"") | C9: =IFERROR(INDEX('Escala de valor'!$E$7:$E$17,MATCH(A9,'Escala de valor'!$A$7:$A$17,0)),"") | D9: 0.1 | E9: =IF(B9="","",B9*(1-D9)) | F9: =IF(OR(B9="",C9="",C9=0),"",E9-C9) | G9: =IF(F9="","",IF(E9=0,"",F9/E9)) | H9: =IF(F9="","Falta costo",IF(G9<0.6,"⚠ CAE BAJO 60%","✅ OK, sobre el piso"))
A10: Láminas 42×60 (grande) | B10: =IFERROR(INDEX('Escala de valor'!$C$7:$C$17,MATCH(A10,'Escala de valor'!$A$7:$A$17,0)),"") | C10: =IFERROR(INDEX('Escala de valor'!$E$7:$E$17,MATCH(A10,'Escala de valor'!$A$7:$A$17,0)),"") | D10: 0.1 | E10: =IF(B10="","",B10*(1-D10)) | F10: =IF(OR(B10="",C10="",C10=0),"",E10-C10) | G10: =IF(F10="","",IF(E10=0,"",F10/E10)) | H10: =IF(F10="","Falta costo",IF(G10<0.6,"⚠ CAE BAJO 60%","✅ OK, sobre el piso"))
A11: Láminas 33×50 (mediana) | B11: =IFERROR(INDEX('Escala de valor'!$C$7:$C$17,MATCH(A11,'Escala de valor'!$A$7:$A$17,0)),"") | C11: =IFERROR(INDEX('Escala de valor'!$E$7:$E$17,MATCH(A11,'Escala de valor'!$A$7:$A$17,0)),"") | D11: 0.1 | E11: =IF(B11="","",B11*(1-D11)) | F11: =IF(OR(B11="",C11="",C11=0),"",E11-C11) | G11: =IF(F11="","",IF(E11=0,"",F11/E11)) | H11: =IF(F11="","Falta costo",IF(G11<0.6,"⚠ CAE BAJO 60%","✅ OK, sobre el piso"))
A12: Libretas | B12: =IFERROR(INDEX('Escala de valor'!$C$7:$C$17,MATCH(A12,'Escala de valor'!$A$7:$A$17,0)),"") | C12: =IFERROR(INDEX('Escala de valor'!$E$7:$E$17,MATCH(A12,'Escala de valor'!$A$7:$A$17,0)),"") | D12: 0.1 | E12: =IF(B12="","",B12*(1-D12)) | F12: =IF(OR(B12="",C12="",C12=0),"",E12-C12) | G12: =IF(F12="","",IF(E12=0,"",F12/E12)) | H12: =IF(F12="","Falta costo",IF(G12<0.6,"⚠ CAE BAJO 60%","✅ OK, sobre el piso"))
A13: Llavero | B13: =IFERROR(INDEX('Escala de valor'!$C$7:$C$17,MATCH(A13,'Escala de valor'!$A$7:$A$17,0)),"") | C13: =IFERROR(INDEX('Escala de valor'!$E$7:$E$17,MATCH(A13,'Escala de valor'!$A$7:$A$17,0)),"") | D13: 0.1 | E13: =IF(B13="","",B13*(1-D13)) | F13: =IF(OR(B13="",C13="",C13=0),"",E13-C13) | G13: =IF(F13="","",IF(E13=0,"",F13/E13)) | H13: =IF(F13="","Falta costo",IF(G13<0.6,"⚠ CAE BAJO 60%","✅ OK, sobre el piso"))
A14: Pins | B14: =IFERROR(INDEX('Escala de valor'!$C$7:$C$17,MATCH(A14,'Escala de valor'!$A$7:$A$17,0)),"") | C14: =IFERROR(INDEX('Escala de valor'!$E$7:$E$17,MATCH(A14,'Escala de valor'!$A$7:$A$17,0)),"") | D14: 0.1 | E14: =IF(B14="","",B14*(1-D14)) | F14: =IF(OR(B14="",C14="",C14=0),"",E14-C14) | G14: =IF(F14="","",IF(E14=0,"",F14/E14)) | H14: =IF(F14="","Falta costo",IF(G14<0.6,"⚠ CAE BAJO 60%","✅ OK, sobre el piso"))
A15: Postales | B15: =IFERROR(INDEX('Escala de valor'!$C$7:$C$17,MATCH(A15,'Escala de valor'!$A$7:$A$17,0)),"") | C15: =IFERROR(INDEX('Escala de valor'!$E$7:$E$17,MATCH(A15,'Escala de valor'!$A$7:$A$17,0)),"") | D15: 0.1 | E15: =IF(B15="","",B15*(1-D15)) | F15: =IF(OR(B15="",C15="",C15=0),"",E15-C15) | G15: =IF(F15="","",IF(E15=0,"",F15/E15)) | H15: =IF(F15="","Falta costo",IF(G15<0.6,"⚠ CAE BAJO 60%","✅ OK, sobre el piso"))
A16: Puzzle (promedio 3 modelos) | B16: =IFERROR(INDEX('Escala de valor'!$C$7:$C$17,MATCH(A16,'Escala de valor'!$A$7:$A$17,0)),"") | C16: =IFERROR(INDEX('Escala de valor'!$E$7:$E$17,MATCH(A16,'Escala de valor'!$A$7:$A$17,0)),"") | D16: 0.1 | E16: =IF(B16="","",B16*(1-D16)) | F16: =IF(OR(B16="",C16="",C16=0),"",E16-C16) | G16: =IF(F16="","",IF(E16=0,"",F16/E16)) | H16: =IF(F16="","Falta costo",IF(G16<0.6,"⚠ CAE BAJO 60%","✅ OK, sobre el piso"))
A17: Totebag | B17: =IFERROR(INDEX('Escala de valor'!$C$7:$C$17,MATCH(A17,'Escala de valor'!$A$7:$A$17,0)),"") | C17: =IFERROR(INDEX('Escala de valor'!$E$7:$E$17,MATCH(A17,'Escala de valor'!$A$7:$A$17,0)),"") | D17: 0.1 | E17: =IF(B17="","",B17*(1-D17)) | F17: =IF(OR(B17="",C17="",C17=0),"",E17-C17) | G17: =IF(F17="","",IF(E17=0,"",F17/E17)) | H17: =IF(F17="","Falta costo",IF(G17<0.6,"⚠ CAE BAJO 60%","✅ OK, sobre el piso"))
A19: Los precios y costos de esta pestaña se traen automáticamente desde Escala de valor (fórmulas INDEX/MATCH) — no se cargan a mano acá. Cambia el producto de cualquier fila (lista desplegable) o el % de descuento, y el resto se recalcula solo. El piso de margen es el mismo 60% de toda la calculadora.

Sheet Forecast por producto
A1: Forecast por producto — demanda de puzzles ago-dic 2026
A2: Los cuatro escenarios de demanda cruzando los tres canales (Shopify, Mercado Libre, B2B), y el reparto de esa demanda por modelo.
A4: A. Demanda por canal, los cuatro escenarios
A5: Escenario | B5: Shopify | C5: Mercado Libre | D5: B2B | E5: Total | F5: Llegan (15-ago) | G5: Faltan
A6: Mínimo | B6: 907 | C6: 454 | D6: 317 | E6: =SUM(B6:D6) | F6: 1290 | G6: =E6-F6
A7: Conservador | B7: 907 | C7: 454 | D7: 796 | E7: =SUM(B7:D7) | F7: 1290 | G7: =E7-F7
A8: Base | B8: 1058 | C8: 665 | D8: 796 | E8: =SUM(B8:D8) | F8: 1290 | G8: =E8-F8
A9: Agresivo | B9: 1058 | C9: 1005 | D9: 796 | E9: =SUM(B9:D9) | F9: 1290 | G9: =E9-F9
A11: Shopify, Mercado Libre y B2B: dato aportado por el operador para este entregable, sobre la base del forecast de tienda propia de docs/forecast-pedido-2026-08-02.md. Llegan: los 1.290 puzzles (incluye 240 de niños) del pedido que llega el 15 de agosto — docs/correcciones-felipe-2026-08-01.md, sección 3.
A13: B. Reparto de esa demanda por modelo (histórico de venta)
A14: % Aves | B14: 0.47 | C14: % Cetáceos | D14: 0.37 | E14: % Hongos | F14: 0.16 | G14: =IF(B14+D14+F14<>1,"⚠ no suma 100%","✅ 100%")
A16: Escenario | B16: Total (de A) | C16: Aves | D16: Cetáceos | E16: Hongos
A17: Mínimo | B17: =E6 | C17: =$B17*$B$14 | D17: =$B17*$D$14 | E17: =$B17*$F$14
A18: Conservador | B18: =E7 | C18: =$B18*$B$14 | D18: =$B18*$D$14 | E18: =$B18*$F$14
A19: Base | B19: =E8 | C19: =$B19*$B$14 | D19: =$B19*$D$14 | E19: =$B19*$F$14
A20: Agresivo | B20: =E9 | C20: =$B20*$B$14 | D20: =$B20*$D$14 | E20: =$B20*$F$14
A22: Reparto 47/37/16: histórico de venta de puzzles grandes, confirmado por Felipe en la llamada del 5 de agosto de 2026 — el mismo reparto que se usa en la pestaña Pedido y en pedido.html. Cambiar los % de arriba recalcula toda la tabla.

Sheet Pedido
A1: Pedido — calculadora del pedido a China
A2: Cambia la cantidad total o el reparto y se recalculan las unidades por modelo, el costo FOB, el costo puesto en Chile y el anticipo del 30%.
A4: Datos generales del pedido
A5: Cantidad total del pedido (unidades) | B5: 2000
A6: Tipo de cambio de referencia (CLP por USD) | B6: 950
A7: % Anticipo a la fábrica (sobre el FOB) | B7: 0.3
A8: Costo puesto en bodega en Chile, por unidad (CLP) | B8: 7253
A10: Reparto por modelo
A11: Modelo | B11: % reparto | C11: Unidades | D11: FOB unitario (USD) | E11: FOB total (USD)
A12: Aves | B12: 0.47 | C12: =$B$5*B12 | D12: 4.8 | E12: =C12*D12
A13: Cetáceos | B13: 0.37 | C13: =$B$5*B13 | D13: 5.8 | E13: =C13*D13
A14: Hongos | B14: 0.16 | C14: =$B$5*B14 | D14: 6.48 | E14: =C14*D14
A15: Total | B15: =SUM(B12:B14) | C15: =SUM(C12:C14) | E15: =SUM(E12:E14)
A16: =IF(B15<>1,"⚠ el reparto no suma 100%","✅ el reparto suma 100%")
A18: Resumen del pedido
A19: Concepto | B19: Monto
A20: FOB total (USD) | B20: =E15
A21: FOB total (CLP) | B21: =B20*B6
A22: Anticipo a la fábrica (USD) | B22: =B20*B7
A23: Anticipo a la fábrica (CLP) — se paga ahora | B23: =B22*B6
A24: Saldo 70% (CLP) — se paga contra entrega | B24: =B21-B23
A25: Costo puesto en bodega en Chile — total | B25: =B5*B8
A26: De eso, logística local (seguro, forwarder, desconsolidación, flete) | B26: =B25-B21
A28: Cuota mensual de los créditos vigentes (referencia de caja) | B28: 1167128
A29: El anticipo equivale a esta cantidad de cuotas mensuales | B29: =B23/B28
A31: Fórmulas verificadas contra la tabla de referencia de docs/forecast-pedido-2026-08-02.md (pedidos de 600/1.000/1.500 unidades, mismo reparto 47/37/16): coinciden al peso. El anticipo es el 30% del FOB (lo que se le paga a la fábrica), no del costo total puesto en Chile — la logística local se paga aparte. Cuota mensual de créditos: docs/datos-financieros-2025-2026.md, sección 6.

Sheet Rotación
A1: Rotación de inventario
A2: Unidades vendidas al mes por categoría, stock actual y meses de cobertura. Alerta cuando quedan menos de 2 meses de stock.
A4: 🟡 Cargar el Stock actual desde Shopify/Bsale para que la cobertura se calcule — hoy solo Puzzle está confirmado (agotado, 0 unidades).
A6: Categoría | B6: Unidades vendidas (18 meses, jul-25 a jun-26) | C6: Velocidad mensual (unid./mes) | D6: Stock actual (completar) | E6: Meses de cobertura | F6: Alerta
A7: Puzzle | B7: 1837 | C7: =B7/18 | D7: 0 | E7: =IF(D7="","",IF(C7=0,"",D7/C7)) | F7: =IF(E7="","Falta stock",IF(E7<2,"🔴 BAJO 2 MESES","🟢 OK"))
A8: Calcetines | B8: 682 | C8: =B8/18 | E8: =IF(D8="","",IF(C8=0,"",D8/C8)) | F8: =IF(E8="","Falta stock",IF(E8<2,"🔴 BAJO 2 MESES","🟢 OK"))
A9: Naipes | B9: 664 | C9: =B9/18 | E9: =IF(D9="","",IF(C9=0,"",D9/C9)) | F9: =IF(E9="","Falta stock",IF(E9<2,"🔴 BAJO 2 MESES","🟢 OK"))
A10: Otros | B10: 566 | C10: =B10/18 | E10: =IF(D10="","",IF(C10=0,"",D10/C10)) | F10: =IF(E10="","Falta stock",IF(E10<2,"🔴 BAJO 2 MESES","🟢 OK"))
A11: Botellas | B11: 320 | C11: =B11/18 | E11: =IF(D11="","",IF(C11=0,"",D11/C11)) | F11: =IF(E11="","Falta stock",IF(E11<2,"🔴 BAJO 2 MESES","🟢 OK"))
A12: Pins | B12: 298 | C12: =B12/18 | E12: =IF(D12="","",IF(C12=0,"",D12/C12)) | F12: =IF(E12="","Falta stock",IF(E12<2,"🔴 BAJO 2 MESES","🟢 OK"))
A13: Llaveros | B13: 268 | C13: =B13/18 | E13: =IF(D13="","",IF(C13=0,"",D13/C13)) | F13: =IF(E13="","Falta stock",IF(E13<2,"🔴 BAJO 2 MESES","🟢 OK"))
A14: Totebags | B14: 164 | C14: =B14/18 | E14: =IF(D14="","",IF(C14=0,"",D14/C14)) | F14: =IF(E14="","Falta stock",IF(E14<2,"🔴 BAJO 2 MESES","🟢 OK"))
A15: Libretas | B15: 154 | C15: =B15/18 | E15: =IF(D15="","",IF(C15=0,"",D15/C15)) | F15: =IF(E15="","Falta stock",IF(E15<2,"🔴 BAJO 2 MESES","🟢 OK"))
A16: Postales | B16: 144 | C16: =B16/18 | E16: =IF(D16="","",IF(C16=0,"",D16/C16)) | F16: =IF(E16="","Falta stock",IF(E16<2,"🔴 BAJO 2 MESES","🟢 OK"))
A17: Total | B17: =SUM(B7:B16)
A19: Unidades vendidas 18 meses (categorías): docs/correcciones-felipe-2026-08-01.md, sección 2 — suman 5.097, igual al total de unidades vendidas en Shopify en el período. Es un promedio de 18 meses, no el ritmo de un mes cualquiera: diciembre vende 3,3 veces un mes normal, así que la velocidad real de fin de año es más alta que este promedio. Puzzle: stock en 0 confirmado — es el quiebre que motivó el pedido a China (docs/datos-financieros-2025-2026.md, sección 8). El resto de los stocks queda por cargar.
